jinad/__init__.py
jinad/config.py
jinad/excepts.py
jinad/helper.py
jinad/main.py
jinad/store.py
jinad/api/__init__.py
jinad/api/endpoints/__init__.py
jinad/api/endpoints/flow.py
jinad/api/endpoints/logs.py
jinad/api/endpoints/pea.py
jinad/api/endpoints/pod.py
jinad/models/__init__.py
jinad/models/custom.py
jinad/models/flow.py
jinad/models/pea.py
jinad/models/pod.py
tests/__init__.py
tests/conftest.py
tests/integration/__init__.py
tests/integration/api/__init__.py
tests/integration/api/endpoints/__init__.py
tests/integration/api/endpoints/test_logging_endpoint.py
tests/unit/__init__.py
tests/unit/test_config.py
tests/unit/test_helper.py
tests/unit/test_main.py
tests/unit/test_store.py
tests/unit/api/__init__.py
tests/unit/api/endpoints/__init__.py
tests/unit/api/endpoints/test_flow.py
tests/unit/api/endpoints/test_pea.py
tests/unit/api/endpoints/test_pod.py
tests/unit/models/__init__.py
tests/unit/models/test_custom.py
tests/unit/models/test_flow.py
tests/unit/models/test_pea.py
tests/unit/models/test_pod.py
jinad-0.0.1.dist-info/LICENSE
jinad-0.0.1.dist-info/METADATA
jinad-0.0.1.dist-info/WHEEL
jinad-0.0.1.dist-info/top_level.txt
jinad-0.0.1.dist-info/RECORD
