Metadata-Version: 2.1
Name: jinad
Version: 0.0.1
Summary: Jinad is the daemon tool for running Jina on remote machines. Jina is the cloud-native neural search solution powered by the state-of-the-art AI and deep learning
Home-page: https://opensource.jina.ai
Author: Jina Dev Team
Author-email: dev-team@jina.ai
License: Apache 2.0
Platform: UNKNOWN
Requires-Python: >=3.6
